cpyment/__init__.py
cpyment/cmodel.py
Compyrtment-0.5.7.dist-info/LICENSE
Compyrtment-0.5.7.dist-info/METADATA
Compyrtment-0.5.7.dist-info/WHEEL
Compyrtment-0.5.7.dist-info/top_level.txt
Compyrtment-0.5.7.dist-info/RECORD
