Metadata-Version: 2.1
Name: Compyrtment
Version: 0.5.7
Summary: A simple Python library for compartment models
Home-page: https://github.com/stur86/compyrtment
Author: Simone Sturniolo
Author-email: simonesturniolo@gmail.com
License: MIT
Keywords: differential equations,compartment models,epidemiology,ecology,reactions,gillespie
Platform: UNKNOWN
Classifier: Development Status :: 4 - Beta
Classifier: Intended Audience :: Education
Classifier: Intended Audience :: Science/Research
Classifier: Topic :: Scientific/Engineering
Classifier: Topic :: Scientific/Engineering :: Artificial Life
Classifier: Topic :: Scientific/Engineering :: Chemistry
Classifier: License :: OSI Approved :: MIT License
Classifier: Programming Language :: Python :: 3
Requires-Python: >=3.6.*
License-File: LICENSE
Requires-Dist: numpy
Requires-Dist: scipy
Requires-Dist: numba
